google/__init__.py
google/api/__init__.py
google/api/annotations_pb2.py
google/api/annotations_pb2.pyi
google/api/field_behavior_pb2.py
google/api/field_behavior_pb2.pyi
google/api/http_pb2.py
google/api/http_pb2.pyi
google/api/httpbody_pb2.py
google/api/httpbody_pb2.pyi
protoc_gen_openapiv2/__init__.py
protoc_gen_openapiv2/options/__init__.py
protoc_gen_openapiv2/options/annotations_pb2.py
protoc_gen_openapiv2/options/annotations_pb2.pyi
protoc_gen_openapiv2/options/openapiv2_pb2.py
protoc_gen_openapiv2/options/openapiv2_pb2.pyi
raystack/__init__.py
raystack/assets/__init__.py
raystack/assets/v1beta1/__init__.py
raystack/assets/v1beta1/bucket_pb2.py
raystack/assets/v1beta1/bucket_pb2.pyi
raystack/assets/v1beta1/dashboard_pb2.py
raystack/assets/v1beta1/dashboard_pb2.pyi
raystack/assets/v1beta1/event_pb2.py
raystack/assets/v1beta1/event_pb2.pyi
raystack/assets/v1beta1/group_pb2.py
raystack/assets/v1beta1/group_pb2.pyi
raystack/assets/v1beta1/job_pb2.py
raystack/assets/v1beta1/job_pb2.pyi
raystack/assets/v1beta1/lineage_pb2.py
raystack/assets/v1beta1/lineage_pb2.pyi
raystack/assets/v1beta1/ownership_pb2.py
raystack/assets/v1beta1/ownership_pb2.pyi
raystack/assets/v1beta1/preview_pb2.py
raystack/assets/v1beta1/preview_pb2.pyi
raystack/assets/v1beta1/properties_pb2.py
raystack/assets/v1beta1/properties_pb2.pyi
raystack/assets/v1beta1/resource_pb2.py
raystack/assets/v1beta1/resource_pb2.pyi
raystack/assets/v1beta1/schema_pb2.py
raystack/assets/v1beta1/schema_pb2.pyi
raystack/assets/v1beta1/table_pb2.py
raystack/assets/v1beta1/table_pb2.pyi
raystack/assets/v1beta1/timestamp_pb2.py
raystack/assets/v1beta1/timestamp_pb2.pyi
raystack/assets/v1beta1/topic_pb2.py
raystack/assets/v1beta1/topic_pb2.pyi
raystack/assets/v1beta1/user_pb2.py
raystack/assets/v1beta1/user_pb2.pyi
raystack/assets/v1beta2/__init__.py
raystack/assets/v1beta2/application_pb2.py
raystack/assets/v1beta2/application_pb2.pyi
raystack/assets/v1beta2/asset_pb2.py
raystack/assets/v1beta2/asset_pb2.pyi
raystack_proton-2026.1.20.64233.dist-info/licenses/LICENSE
raystack_proton-2026.1.20.64233.dist-info/METADATA
raystack_proton-2026.1.20.64233.dist-info/WHEEL
raystack_proton-2026.1.20.64233.dist-info/top_level.txt
raystack_proton-2026.1.20.64233.dist-info/RECORD
