Metadata-Version: 2.4
Name: raystack-proton
Version: 2026.1.20.64233
Summary: Python client library for Raystack services
Author: Raystack
License-Expression: Apache-2.0
Project-URL: Homepage, https://github.com/raystack/proton
Project-URL: Repository, https://github.com/raystack/proton
Requires-Python: >=3.8
License-File: LICENSE
Requires-Dist: connect-python==0.5.0
Requires-Dist: googleapis-common-protos>=1.50.0
Requires-Dist: grpcio>=1.50.0
Requires-Dist: protobuf<7.0.0,>=4.21.0
Dynamic: license-file
